datasette_render_local_images/__init__.py
datasette_render_local_images-0.0.8.dist-info/LICENSE
datasette_render_local_images-0.0.8.dist-info/METADATA
datasette_render_local_images-0.0.8.dist-info/WHEEL
datasette_render_local_images-0.0.8.dist-info/entry_points.txt
datasette_render_local_images-0.0.8.dist-info/top_level.txt
datasette_render_local_images-0.0.8.dist-info/RECORD
