Metadata-Version: 2.1
Name: datasette-render-local-images
Version: 0.0.8
Summary: Render local images in the system using datasette plugin
Home-page: https://github.com/kracekumar/datasette-render-local-images
Author: Kracekumar
License: Apache License, Version 2.0
Project-URL: Issues, https://github.com/kracekumar/datasette-render-local-images/issues
Project-URL: CI, https://github.com/kracekumar/datasette-render-local-images/actions
Project-URL: Changelog, https://github.com/kracekumar/datasette-render-local-images/releases
Platform: UNKNOWN
Requires-Dist: datasette
Provides-Extra: test
Requires-Dist: pytest ; extra == 'test'
Requires-Dist: pytest-asyncio ; extra == 'test'
Requires-Dist: httpx ; extra == 'test'
Requires-Dist: sqlite-utils ; extra == 'test'
Requires-Dist: coverage (==5.3) ; extra == 'test'
Requires-Dist: pytest-coverage ; extra == 'test'
